Metadata-Version: 2.1
Name: pybde
Version: 0.4.2
Summary: Boolean Delay Equation simulator
Home-page: https://github.com/EPCCed/pybde/wiki/pybde
Author: Ally Hume
Author-email: a.hume@epcc.ed.ac.uk
License: MIT
Keywords: BDE,boolean,delay,equations,solver,simulator
Platform: UNKNOWN
Classifier: Development Status :: 3 - Alpha
Classifier: License :: OSI Approved :: MIT License
Classifier: Programming Language :: Python :: 3.5
Classifier: Programming Language :: Python :: 3.6
Classifier: Programming Language :: Python :: 3.7
Classifier: Programming Language :: Python :: 3.8
Classifier: Topic :: Scientific/Engineering
Classifier: Operating System :: OS Independent
Requires-Python: >=3.5
